feffery_utils_components/FefferyAPlayer.py
feffery_utils_components/FefferyAnimatedImage.py
feffery_utils_components/FefferyAutoAnimate.py
feffery_utils_components/FefferyAutoFit.py
feffery_utils_components/FefferyBarcode.py
feffery_utils_components/FefferyBirdsBackground.py
feffery_utils_components/FefferyBlockColorPicker.py
feffery_utils_components/FefferyBurger.py
feffery_utils_components/FefferyCaptcha.py
feffery_utils_components/FefferyCellsBackground.py
feffery_utils_components/FefferyCircleColorPicker.py
feffery_utils_components/FefferyCloudsBackground.py
feffery_utils_components/FefferyCloudsTwoBackground.py
feffery_utils_components/FefferyCompareSlider.py
feffery_utils_components/FefferyCookie.py
feffery_utils_components/FefferyCountDown.py
feffery_utils_components/FefferyCountUp.py
feffery_utils_components/FefferyCssVar.py
feffery_utils_components/FefferyDPlayer.py
feffery_utils_components/FefferyDebounceProp.py
feffery_utils_components/FefferyDebugGuardian.py
feffery_utils_components/FefferyDeviceDetect.py
feffery_utils_components/FefferyDiv.py
feffery_utils_components/FefferyDocumentVisibility.py
feffery_utils_components/FefferyDom2Image.py
feffery_utils_components/FefferyDownload.py
feffery_utils_components/FefferyDraggable.py
feffery_utils_components/FefferyEmojiPicker.py
feffery_utils_components/FefferyEventListener.py
feffery_utils_components/FefferyEventSource.py
feffery_utils_components/FefferyExcelPreview.py
feffery_utils_components/FefferyExecuteJs.py
feffery_utils_components/FefferyExternalCss.py
feffery_utils_components/FefferyExternalJs.py
feffery_utils_components/FefferyExtraSpinner.py
feffery_utils_components/FefferyEyeDropper.py
feffery_utils_components/FefferyFancyButton.py
feffery_utils_components/FefferyFancyMessage.py
feffery_utils_components/FefferyFancyNotification.py
feffery_utils_components/FefferyFixed.py
feffery_utils_components/FefferyFogBackground.py
feffery_utils_components/FefferyFormatBytes.py
feffery_utils_components-0.3.5.dist-info/licenses/LICENSE
feffery_utils_components-0.3.5.dist-info/METADATA
feffery_utils_components-0.3.5.dist-info/WHEEL
feffery_utils_components-0.3.5.dist-info/top_level.txt
feffery_utils_components-0.3.5.dist-info/RECORD
