Metadata-Version: 2.4
Name: feffery_utils_components
Version: 0.3.5
Summary: Build more utility components for Plotly Dash.
Home-page: https://github.com/CNFeffery/feffery-utils-components
Author: CNFeffery <fefferypzy@gmail.com>
Author-email: fefferypzy@gmail.com
License: MIT
Classifier: Framework :: Dash
License-File: LICENSE
Requires-Dist: dash>=3.1.0
Dynamic: author
Dynamic: author-email
Dynamic: classifier
Dynamic: description
Dynamic: description-content-type
Dynamic: home-page
Dynamic: license
Dynamic: license-file
Dynamic: requires-dist
Dynamic: summary
